setup.py
gabin/BinomialDistribution.py
gabin/GaussianDistribution.py
gabin/GeneralDistribution.py
gabin/__init__.py
gabin.egg-info/PKG-INFO
gabin.egg-info/SOURCES.txt
gabin.egg-info/dependency_links.txt
gabin.egg-info/not-zip-safe
gabin.egg-info/top_level.txt