Metadata-Version: 1.0
Name: gabin
Version: 0.1
Summary: Gaussian and Binomial distributions
Home-page: UNKNOWN
Author: Lakshya Bansal
Author-email: bansallakshya94128@gmail.com
License: UNKNOWN
Platform: UNKNOWN
